auxlib/.version
auxlib/__init__.py
auxlib/collection.py
auxlib/compat.py
auxlib/configuration.py
auxlib/crypt.py
auxlib/decorators.py
auxlib/deprecation.py
auxlib/entity.py
auxlib/exceptions.py
auxlib/factory.py
auxlib/ish.py
auxlib/logz.py
auxlib/packaging.py
auxlib/path.py
auxlib/type_coercion.py
auxlib/_vendor/__init__.py
auxlib/_vendor/five.py
auxlib/_vendor/six.py
auxlib/_vendor/boltons/__init__.py
auxlib/_vendor/boltons/timeutils.py
auxlib-0.0.43.dist-info/LICENSE
auxlib-0.0.43.dist-info/METADATA
auxlib-0.0.43.dist-info/WHEEL
auxlib-0.0.43.dist-info/pbr.json
auxlib-0.0.43.dist-info/top_level.txt
auxlib-0.0.43.dist-info/RECORD
